plutus/__init__.py
plutus/utils.py
plutus/core/__init__.py
plutus/core/algorithm.py
plutus/core/bot.py
plutus/core/constant.py
plutus/core/instrument.py
plutus/core/order.py
plutus/core/portfolio.py
plutus/core/position.py
plutus/core/transaction.py
plutus/data/__init__.py
plutus/data/asyncdatahub.py
plutus/data/csv_interface.py
plutus/data/csv_metadata_reader.py
plutus/data/csv_parser_mixin.py
plutus/data/csv_quote_reader.py
plutus/data/data_handler.py
plutus/data/datahub.py
plutus/data/filter.py
plutus/data/redis_datahub.py
plutus/data/model/README.md
plutus/data/model/__init__.py
plutus/data/model/enums.py
plutus/data/model/metadata.py
plutus/data/model/quote.py
plutus/data/model/quote_named_tuple.py
plutus/datahub/__init__.py
plutus/datahub/__main__.py
plutus/datahub/cli_optimize.py
plutus/datahub/config.py
plutus/datahub/ohlc_query.py
plutus/datahub/result_iterator.py
plutus/datahub/tick_query.py
plutus/datahub/cache/__init__.py
plutus/datahub/cache/metadata_cache.py
plutus/datahub/converters/__init__.py
plutus/datahub/converters/parquet_converter.py
plutus/datahub/docs/CLI_USAGE_GUIDE.md
plutus/datahub/docs/DATA_OPTIMIZATION_GUIDE.md
plutus/datahub/utils/__init__.py
plutus/datahub/utils/date_utils.py
plutus/evaluation/__init__.py
plutus/evaluation/performance.py
plutus/evaluation/metrics/__init__.py
plutus/evaluation/metrics/drawdown.py
plutus/evaluation/metrics/returns.py
plutus/evaluation/metrics/risk.py
plutus/experiment/README.md
plutus/experiment/__init__.py
plutus/experiment/benchmarking/__init__.py
plutus/experiment/benchmarking/quote_benchmarking.py
plutus/experiment/benchmarking/legacy/legacy_memory_benchmark.py
plutus/experiment/benchmarking/legacy/legacy_speed_benchmark.py
plutus/experiment/benchmarking/report/performance_analysis.md
plutus/experiment/benchmarking/report/quote_implementation_benchmark_result_20250925_171730.txt
plutus/experiment/investigation/__init__.py
plutus/experiment/investigation/quote_dynamic_dict.py
algotrade_plutus-0.2.5.20251023.dist-info/METADATA
algotrade_plutus-0.2.5.20251023.dist-info/WHEEL
algotrade_plutus-0.2.5.20251023.dist-info/entry_points.txt
algotrade_plutus-0.2.5.20251023.dist-info/licenses/LICENSE
algotrade_plutus-0.2.5.20251023.dist-info/RECORD
