Metadata-Version: 2.4
Name: algotrade-plutus
Version: 0.2.5.20251023
Summary: Zero-setup market data analytics with Python API, CLI, and LLM integration
Project-URL: Homepage, https://github.com/algotradevn/plutus
Project-URL: Documentation, https://github.com/algotradevn/plutus/docs
Project-URL: Repository, https://github.com/algotradevn/plutus
Project-URL: Issues, https://github.com/algotradevn/plutus/issues
Author-email: Dan <andan@algotrade.vn>
License: MIT
License-File: LICENSE
Keywords: algorithmic-trading,llm,market-data,mcp,trading,vietnamese-stocks
Classifier: Development Status :: 5 - Production/Stable
Classifier: Intended Audience :: Developers
Classifier: Intended Audience :: Financial and Insurance Industry
Classifier: License :: OSI Approved :: MIT License
Classifier: Operating System :: OS Independent
Classifier: Programming Language :: Python :: 3
Classifier: Programming Language :: Python :: 3.12
Classifier: Programming Language :: Python :: 3.13
Classifier: Topic :: Office/Business :: Financial :: Investment
Classifier: Topic :: Scientific/Engineering :: Information Analysis
Requires-Python: >=3.12
Requires-Dist: duckdb>=1.0.0
Requires-Dist: pandas>=2.0.0
Requires-Dist: pyarrow>=12.0.0
Requires-Dist: pytz>=2024.1
Provides-Extra: all
Requires-Dist: plutus[dev,mcp]; extra == 'all'
Provides-Extra: dev
Requires-Dist: build>=1.0.0; extra == 'dev'
Requires-Dist: pytest>=8.0.0; extra == 'dev'
Provides-Extra: legacy
Requires-Dist: redis>=5.0.0; extra == 'legacy'
Requires-Dist: ujson>=5.0.0; extra == 'legacy'
Provides-Extra: mcp
Requires-Dist: fastmcp>=2.0.0; extra == 'mcp'
Requires-Dist: pydantic>=2.0.0; extra == 'mcp'
